odoo/addons/l10n_ro_stock/README.rst
odoo/addons/l10n_ro_stock/__init__.py
odoo/addons/l10n_ro_stock/__manifest__.py
odoo/addons/l10n_ro_stock/data/stock_data.xml
odoo/addons/l10n_ro_stock/i18n/l10n_ro_stock.pot
odoo/addons/l10n_ro_stock/i18n/ro.po
odoo/addons/l10n_ro_stock/models/__init__.py
odoo/addons/l10n_ro_stock/models/product_template.py
odoo/addons/l10n_ro_stock/models/res_company.py
odoo/addons/l10n_ro_stock/models/stock_location.py
odoo/addons/l10n_ro_stock/models/stock_move.py
odoo/addons/l10n_ro_stock/models/stock_warehouse.py
odoo/addons/l10n_ro_stock/readme/CONTRIBUTORS.md
odoo/addons/l10n_ro_stock/readme/DESCRIPTION.md
odoo/addons/l10n_ro_stock/readme/INSTALL.md
odoo/addons/l10n_ro_stock/static/description/icon.png
odoo/addons/l10n_ro_stock/static/description/index.html
odoo/addons/l10n_ro_stock/tests/__init__.py
odoo/addons/l10n_ro_stock/tests/test_stock_warehouse_creation.py
odoo/addons/l10n_ro_stock/views/product_template_view.xml
odoo/addons/l10n_ro_stock/views/stock_warehouse_view.xml
odoo_addon_l10n_ro_stock-19.0.0.3.0.2.dist-info/METADATA
odoo_addon_l10n_ro_stock-19.0.0.3.0.2.dist-info/WHEEL
odoo_addon_l10n_ro_stock-19.0.0.3.0.2.dist-info/top_level.txt
odoo_addon_l10n_ro_stock-19.0.0.3.0.2.dist-info/RECORD
